symmat/__init__.py
symmat/version.py
symmat-0.1.0.dist-info/METADATA
symmat-0.1.0.dist-info/WHEEL
symmat-0.1.0.dist-info/top_level.txt
symmat-0.1.0.dist-info/RECORD
