Metadata-Version: 2.1
Name: symmat
Version: 0.1.0
Summary: symmat
Home-page: https://symmat.github.io
Author: Zhiqing Xiao
Author-email: xzq.xiaozhiqing@gmail.com
Classifier: Development Status :: 3 - Alpha
Classifier: Programming Language :: Python
Classifier: Intended Audience :: Science/Research
